modstore-3.0.0.dist-info/METADATA
modstore-3.0.0.dist-info/WHEEL
modstore-3.0.0.dist-info/licenses/LICENSE
modstore/tools/__init__.py
modstore/tools/typing.pyi
modstore/tools/typing.py
modstore/_binaries.pyi
modstore/python/queue.py
modstore/python/tree.py
modstore/python/stack.pyi
modstore/python/list.py
modstore/python/linkedlist.py
modstore/python/linkedlist.pyi
modstore/python/__init__.py
modstore/python/hashmap.pyi
modstore/python/Math/constants.py
modstore/python/Math/__init__.py
modstore/python/tree3.py
modstore/python/tree2.py
modstore/python/stack.py
modstore/python/queue.pyi
modstore/python/list.pyi
modstore/python/string.py
modstore/python/hashmap.py
modstore/datastructures/__init__.py
modstore/rust/dag.py
modstore/rust/__init__.py
modstore/rust/blockchain.py
modstore/algorithms/searching/_searching.py
modstore/algorithms/searching/__init__.py
modstore/algorithms/searching/_searching.pyi
modstore/algorithms/__init__.py
modstore/algorithms/sorting/__init__.py
modstore/algorithms/sorting/_sorting.py
modstore/algorithms/sorting/_sorting.pyi
modstore/__init__.py
modstore/exceptions/algorithms.py
modstore/exceptions/tools.py
modstore/exceptions/__init__.py
modstore/exceptions/algorithms.pyi
modstore/exceptions/_utils.pyi
modstore/exceptions/python.pyi
modstore/exceptions/python.py
modstore/exceptions/tools.pyi
modstore/exceptions/_utils.py
modstore/_binaries.cpython-312-darwin.so
modstore-3.0.0.dist-info/RECORD
