Metadata-Version: 2.4
Name: modstore
Version: 3.0.0
Classifier: Development Status :: 5 - Production/Stable
Classifier: Intended Audience :: Developers
Classifier: Topic :: Software Development :: Build Tools
Classifier: Programming Language :: Python :: 3.8
Classifier: Programming Language :: Python :: 3.9
Classifier: Programming Language :: Python :: 3.10
Classifier: Programming Language :: Python :: 3.11
Classifier: Programming Language :: Python :: 3.12
Classifier: Programming Language :: Python :: 3.13
Classifier: License :: OSI Approved :: MIT License
Classifier: Operating System :: MacOS :: MacOS X
Classifier: Operating System :: POSIX :: Linux
Classifier: Operating System :: Microsoft :: Windows
Classifier: Programming Language :: Python :: 3
Classifier: Programming Language :: Python :: 3 :: Only
Requires-Dist: maturin
Requires-Dist: tabulate
License-File: LICENSE
Summary: Basic and Modded data structures with rust backend for speed.
Author-email: Soumyo Deep Gupta <deep.main.ac@gmail.com>
Maintainer-email: Soumyo Deep Gupta <deep.main.ac@gmail.com>
Requires-Python: >=3.8
Project-URL: Documentation, https://d33p0st.in/documentation/libraries/modstore/#libraries
Project-URL: GitHub, https://github.com/d33p0st/modstore
Project-URL: Pull-Requests, https://github.com/d33p0st/modstore/pulls
Project-URL: Issues, https://github.com/d33p0st/modstore/issues
